atomic_operator_runner/__init__.py
atomic_operator_runner/__main__.py
atomic_operator_runner/aws.py
atomic_operator_runner/base.py
atomic_operator_runner/data/logging.yml
atomic_operator_runner/local.py
atomic_operator_runner/models.py
atomic_operator_runner/processor.py
atomic_operator_runner/py.typed
atomic_operator_runner/remote.py
atomic_operator_runner/runner.py
atomic_operator_runner/utils/__init__.py
atomic_operator_runner/utils/exceptions.py
atomic_operator_runner/utils/logger.py
atomic_operator_runner-0.2.1.dist-info/METADATA
atomic_operator_runner-0.2.1.dist-info/entry_points.txt
atomic_operator_runner-0.2.1.dist-info/WHEEL
atomic_operator_runner-0.2.1.dist-info/LICENSE
atomic_operator_runner-0.2.1.dist-info/RECORD
