Metadata-Version: 2.1
Name: atomic-operator-runner
Version: 0.2.1
Summary: atomic-operator-runner
Home-page: https://github.com/swimlane/atomic-operator-runner
License: MIT
Author: Josh Rickard
Author-email: rickardja@live.com
Requires-Python: >=3.7,<4.0
Classifier: Development Status :: 2 - Pre-Alpha
Classifier: License :: OSI Approved :: MIT License
Classifier: Programming Language :: Python :: 3
Classifier: Programming Language :: Python :: 3.7
Classifier: Programming Language :: Python :: 3.8
Classifier: Programming Language :: Python :: 3.9
Classifier: Programming Language :: Python :: 3.10
Classifier: Programming Language :: Python :: 3.11
Requires-Dist: PyYAML (>=6.0,<7.0)
Requires-Dist: click (>=8.0.1)
Requires-Dist: paramiko (>=2.11.0,<3.0.0)
Requires-Dist: pydantic (>=1.10.1,<2.0.0)
Requires-Dist: pypsrp (>=0.8.1,<0.9.0)
Requires-Dist: requests (>=2.28.1,<3.0.0)
Project-URL: Changelog, https://github.com/swimlane/atomic-operator-runner/releases
Project-URL: Documentation, https://atomic-operator.com
Project-URL: Repository, https://github.com/swimlane/atomic-operator-runner
